{
  "books": [
    {
      "id": 102,
      "author": "Dante Alighieri",
      "country": "Italy",
      "imageLink": "images/the-divine-comedy.jpg",
      "language": "Italian",
      "link": "https://en.wikipedia.org/wiki/Divine_Comedy\n",
      "pages": 928,
      "title": "The Divine Comedy",
      "year": 1315
    },
    {
      "id": 103,
      "author": "Jane Austen",
      "country": "United Kingdom",
      "imageLink": "images/pride-and-prejudice.jpg",
      "language": "English",
      "link": "https://en.wikipedia.org/wiki/Pride_and_Prejudice\n",
      "pages": 226,
      "title": "Pride and Prejudice",
      "year": 1813
    },
    {
      "id": 104,
      "author": "Giovanni Boccaccio",
      "country": "Italy",
      "imageLink": "images/the-decameron.jpg",
      "language": "Italian",
      "link": "https://en.wikipedia.org/wiki/The_Decameron\n",
      "pages": 1024,
      "title": "The Decameron",
      "year": 1351
    },
    {
      "id": 105,
      "author": "Jorge Luis Borges",
      "country": "Argentina",
      "imageLink": "images/ficciones.jpg",
      "language": "Spanish",
      "link": "https://en.wikipedia.org/wiki/Ficciones\n",
      "pages": 224,
      "title": "Ficciones",
      "year": 1965
    },
    {
      "id": 106,
      "author": "Albert Camus",
      "country": "Algeria, French Empire",
      "imageLink": "images/l-etranger.jpg",
      "language": "French",
      "link": "https://en.wikipedia.org/wiki/The_Stranger_(novel)\n",
      "pages": 185,
      "title": "The Stranger",
      "year": 1942
    },
    {
      "id": 107,
      "author": "Miguel de Cervantes",
      "country": "Spain",
      "imageLink": "images/don-quijote-de-la-mancha.jpg",
      "language": "Spanish",
      "link": "https://en.wikipedia.org/wiki/Don_Quixote\n",
      "pages": 1056,
      "title": "Don Quijote De La Mancha",
      "year": 1610
    },
    {
      "id": 130,
      "author": "Fyodor Dostoevsky",
      "country": "Russia",
      "imageLink": "images/crime-and-punishment.jpg",
      "language": "Russian",
      "link": "https://en.wikipedia.org/wiki/Crime_and_Punishment\n",
      "pages": 551,
      "title": "Crime and Punishment",
      "year": 1866
    },
    {
      "id": 112,
      "author": "Fyodor Dostoevsky",
      "country": "Russia",
      "imageLink": "images/the-idiot.jpg",
      "language": "Russian",
      "link": "https://en.wikipedia.org/wiki/The_Idiot\n",
      "pages": 656,
      "title": "The Idiot",
      "year": 1869
    },
    {
      "id": 115,
      "author": "Gabriel García Márquez",
      "country": "Colombia",
      "imageLink": "images/one-hundred-years-of-solitude.jpg",
      "language": "Spanish",
      "link": "https://en.wikipedia.org/wiki/One_Hundred_Years_of_Solitude\n",
      "pages": 417,
      "title": "One Hundred Years of Solitude",
      "year": 1967
    },
    {
      "id": 116,
      "author": "Gabriel García Márquez",
      "country": "Colombia",
      "imageLink": "images/love-in-the-time-of-cholera.jpg",
      "language": "Spanish",
      "link": "https://en.wikipedia.org/wiki/Love_in_the_Time_of_Cholera\n",
      "pages": 368,
      "title": "Love in the Time of Cholera",
      "year": 1985
    },
    {
      "id": 118,
      "author": "João Guimarães Rosa",
      "country": "Brazil",
      "imageLink": "images/the-devil-to-pay-in-the-backlands.jpg",
      "language": "Portuguese",
      "link": "https://en.wikipedia.org/wiki/The_Devil_to_Pay_in_the_Backlands\n",
      "pages": 494,
      "title": "The Devil to Pay in the Backlands",
      "year": 1956
    },
    {
      "id": 130,
      "author": "Franz Kafka",
      "country": "Czechoslovakia",
      "imageLink": "images/the-trial.jpg",
      "language": "German",
      "link": "https://en.wikipedia.org/wiki/The_Trial\n",
      "pages": 160,
      "title": "The Trial",
      "year": 1925
    },
    {
      "id": 125,
      "author": "George Orwell",
      "country": "United Kingdom",
      "imageLink": "images/nineteen-eighty-four.jpg",
      "language": "English",
      "link": "https://en.wikipedia.org/wiki/Nineteen_Eighty-Four\n",
      "pages": 272,
      "title": "Nineteen Eighty-Four",
      "year": 1949
    },
    {
      "id": 132,
      "author": "Italo Svevo",
      "country": "Italy",
      "imageLink": "images/confessions-of-zeno.jpg",
      "language": "Italian",
      "link": "https://en.wikipedia.org/wiki/Zeno%27s_Conscience\n",
      "pages": 412,
      "title": "Confessions of Zeno",
      "year": 1923
    }
  ]
}